Sim3DR_Cython.cpython-39-x86_64-linux-gnu.so
bev/__init__.py
bev/main.py
bev/model.py
bev/pack_smil_info.py
bev/post_parser.py
bev/split2process.py
romp/__init__.py
romp/main.py
romp/model.py
romp/pack_smpl_info.py
romp/post_parser.py
romp/smpl.py
romp/utils.py
trace2/__init__.py
trace2/eval.py
trace2/main.py
trace2/show.py
trace2/track.py
trace2/evaluation/__init__.py
trace2/evaluation/eval_3DPW.py
trace2/evaluation/eval_dynacam.py
trace2/evaluation/evaluate_tracking.py
trace2/evaluation/evaluation.py
trace2/evaluation/smpl.py
trace2/evaluation/TrackEval/setup.py
trace2/evaluation/TrackEval/trackeval/__init__.py
trace2/evaluation/TrackEval/trackeval/_timing.py
trace2/evaluation/TrackEval/trackeval/eval.py
trace2/evaluation/TrackEval/trackeval/plotting.py
trace2/evaluation/TrackEval/trackeval/utils.py
trace2/evaluation/TrackEval/trackeval/baselines/__init__.py
trace2/evaluation/TrackEval/trackeval/baselines/baseline_utils.py
trace2/evaluation/TrackEval/trackeval/baselines/non_overlap.py
trace2/evaluation/TrackEval/trackeval/baselines/pascal_colormap.py
trace2/evaluation/TrackEval/trackeval/baselines/stp.py
trace2/evaluation/TrackEval/trackeval/baselines/thresholder.py
trace2/evaluation/TrackEval/trackeval/baselines/vizualize.py
trace2/evaluation/TrackEval/trackeval/datasets/__init__.py
trace2/evaluation/TrackEval/trackeval/datasets/_base_dataset.py
trace2/evaluation/TrackEval/trackeval/datasets/bdd100k.py
trace2/evaluation/TrackEval/trackeval/datasets/davis.py
trace2/evaluation/TrackEval/trackeval/datasets/head_tracking_challenge.py
trace2/evaluation/TrackEval/trackeval/datasets/kitti_2d_box.py
trace2/evaluation/TrackEval/trackeval/datasets/kitti_mots.py
trace2/evaluation/TrackEval/trackeval/datasets/mot_challenge_2d_box.py
trace2/evaluation/TrackEval/trackeval/datasets/mots_challenge.py
trace2/evaluation/TrackEval/trackeval/datasets/rob_mots.py
trace2/evaluation/TrackEval/trackeval/datasets/rob_mots_classmap.py
simple_romp-2.0.2.dist-info/LICENSE
simple_romp-2.0.2.dist-info/METADATA
simple_romp-2.0.2.dist-info/WHEEL
simple_romp-2.0.2.dist-info/entry_points.txt
simple_romp-2.0.2.dist-info/top_level.txt
simple_romp-2.0.2.dist-info/RECORD
