Metadata-Version: 2.1
Name: simple-romp
Version: 2.0.2
Summary: ROMP [ICCV21], BEV [CVPR22], TRACE [CVPR23]
Home-page: https://github.com/Arthur151/ROMP
Author: Yu Sun
Author-email: yusunhit@gmail.com
License: UNKNOWN
Project-URL: Bug Tracker, https://github.com/Arthur151/ROMP/issues
Platform: UNKNOWN
Classifier: Programming Language :: Python :: 3
Classifier: License :: Other/Proprietary License
Classifier: Operating System :: OS Independent
Requires-Dist: opencv-python
Requires-Dist: torch
Requires-Dist: setuptools (>=18.0.0)
Requires-Dist: cython
Requires-Dist: numpy (>=1.21.0)
Requires-Dist: typing-extensions (>=4.1)
Requires-Dist: scipy
Requires-Dist: lap
